py_star/config.py
py_star/__init__.py
py_star/agi.py
py_star/agitb.py
py_star/manager.py
py_star/compat.py
py_star/astemu.py
py_star-0.1.0.dev1.dist-info/RECORD
py_star-0.1.0.dev1.dist-info/METADATA
py_star-0.1.0.dev1.dist-info/WHEEL
py_star-0.1.0.dev1.dist-info/metadata.json
py_star-0.1.0.dev1.dist-info/top_level.txt
py_star-0.1.0.dev1.dist-info/DESCRIPTION.rst
