Metadata-Version: 2.0
Name: py-star
Version: 0.1.0.dev1
Summary: A Python Interface to Asterisk
Home-page: https://github.com/medularis/py-star
Author: German Larrain
Author-email: glarrain@users.noreply.github.com
License: 3-clause BSD
Platform: Any
Classifier: Development Status :: 4 - Beta
Classifier: Environment :: Other Environment
Classifier: Intended Audience :: Developers
Classifier: Intended Audience :: Telecommunications Industry
Classifier: Operating System :: OS Independent
Classifier: Programming Language :: Python
Classifier: Programming Language :: Python :: 2.6
Classifier: Programming Language :: Python :: 2.7
Classifier: Topic :: Communications :: Internet Phone
Classifier: Topic :: Communications :: Telephony
Classifier: Topic :: Software Development :: Libraries :: Python Modules
Classifier: License :: OSI Approved :: BSD License
